domain_events/__init__.py
domain_events/base.py
domain_events/config.py
domain_events/dispatcher.py
domain_events/django.py
domain_events/registry.py
domain_events/system.py
domain_events/tasks.py
fast_python_events-1.0.0.dist-info/METADATA
fast_python_events-1.0.0.dist-info/WHEEL
fast_python_events-1.0.0.dist-info/top_level.txt
fast_python_events-1.0.0.dist-info/RECORD
