Metadata-Version: 2.4
Name: fast-python-events
Version: 1.0.0
Summary: A high-performance domain events library for Python applications.
Author-email: Joaquín <jota.dev.es@gmail.com>
License-Expression: MIT
Project-URL: Homepage, https://github.com/jotauses/fast-python-events/
Project-URL: Repository, https://github.com/jotauses/fast-python-events/
Keywords: events,domain,django,fastapi,celery,performance
Classifier: Development Status :: 4 - Beta
Classifier: Intended Audience :: Developers
Classifier: Operating System :: OS Independent
Classifier: Programming Language :: Python :: 3
Classifier: Programming Language :: Python :: 3.8
Classifier: Programming Language :: Python :: 3.9
Classifier: Programming Language :: Python :: 3.10
Classifier: Programming Language :: Python :: 3.11
Classifier: Programming Language :: Python :: 3.12
Classifier: Programming Language :: Python :: 3.13
Requires-Python: >=3.8
Requires-Dist: celery>=5.0.0
Provides-Extra: dev
Requires-Dist: pytest>=6.0; extra == "dev"
Requires-Dist: pytest-cov; extra == "dev"
Requires-Dist: black; extra == "dev"
Requires-Dist: isort; extra == "dev"
Requires-Dist: mypy; extra == "dev"
Dynamic: requires-python
